AUTHORS.rst
CONTRIBUTING.rst
HISTORY.rst
LICENSE
MANIFEST.in
README.rst
setup.cfg
setup.py
docs/Makefile
docs/authors.rst
docs/conf.py
docs/contributing.rst
docs/history.rst
docs/index.rst
docs/installation.rst
docs/make.bat
docs/readme.rst
docs/usage.rst
sourcy/__init__.py
sourcy/language.py
sourcy/parser.py
sourcy.egg-info/PKG-INFO
sourcy.egg-info/SOURCES.txt
sourcy.egg-info/dependency_links.txt
sourcy.egg-info/entry_points.txt
sourcy.egg-info/not-zip-safe
sourcy.egg-info/requires.txt
sourcy.egg-info/top_level.txt
sourcy/cli/__init__.py
sourcy/cli/download.py
sourcy/grammars/languages.so
sourcy/tokens/__init__.py
sourcy/tokens/doc.py
sourcy/tokens/token.py
tests/__init__.py
tests/test_sourcy.py
tests/resources/SignerOutputStream.identifiers.gold
tests/resources/SignerOutputStream.java
tests/resources/SignerOutputStream.tokens.gold