Metadata-Version: 1.2
Name: sourcy
Version: 0.2.2
Summary: A library for Natural Language Processing style preprocessing for source code in different languages
Home-page: https://github.com/SasCezar/sourcy
Author: Cezar Sas
Author-email: cezar.sas@gmail.com
License: GNU General Public License v3
Keywords: sourcy
Platform: UNKNOWN
Classifier: Development Status :: 2 - Pre-Alpha
Classifier: Intended Audience :: Developers
Classifier: License :: OSI Approved :: GNU General Public License v3 (GPLv3)
Classifier: Natural Language :: English
Classifier: Programming Language :: Python :: 3
Classifier: Programming Language :: Python :: 3.5
Classifier: Programming Language :: Python :: 3.6
Classifier: Programming Language :: Python :: 3.7
Classifier: Programming Language :: Python :: 3.8
Requires-Python: >=3.5
